pylogfloat/PyLogFloat.py
pylogfloat/__init__.py
pylogfloat-0.1.4.dist-info/METADATA
pylogfloat-0.1.4.dist-info/WHEEL
pylogfloat-0.1.4.dist-info/top_level.txt
pylogfloat-0.1.4.dist-info/RECORD
